pysplash/__init__.py
pysplash/gdm3changer.py
pysplash/lightdmchanger.py
pySplash-0.0.1.dist-info/LICENSE
pySplash-0.0.1.dist-info/METADATA
pySplash-0.0.1.dist-info/WHEEL
pySplash-0.0.1.dist-info/top_level.txt
pySplash-0.0.1.dist-info/RECORD
