Metadata-Version: 2.1
Name: pySplash
Version: 0.0.1
Summary: A simple wallpaper changer
Home-page: https://gitlab.com/rouvenhimmelstein/pysplash
Author: RouHim
Author-email: rouvenhimmelstein@gmail.com
License: GNU General Public License v3.0
Platform: UNKNOWN
Classifier: Programming Language :: Python :: 3
Classifier: License :: OSI Approved :: GNU General Public License v3 (GPLv3)
Classifier: Operating System :: OS Independent
Requires-Dist: screeninfo
